message_transform/__init__.py
message_transform/message_transform.py
message_transform-1.1.2.dist-info/DESCRIPTION.rst
message_transform-1.1.2.dist-info/METADATA
message_transform-1.1.2.dist-info/RECORD
message_transform-1.1.2.dist-info/WHEEL
message_transform-1.1.2.dist-info/metadata.json
message_transform-1.1.2.dist-info/top_level.txt
