Metadata-Version: 2.0
Name: message-transform
Version: 1.1.2
Summary: Fast, simple message transforms
Provides-Extra: dev
Requires-Dist: check-manifest; extra == 'dev'
Provides-Extra: test
Requires-Dist: pytest; extra == 'test'
Requires-Dist: sys; extra == 'test'
